sqzhash/__init__.py
sqzhash/sqzhash.py
sqzhash-1.0.2.dist-info/LICENSE
sqzhash-1.0.2.dist-info/METADATA
sqzhash-1.0.2.dist-info/WHEEL
sqzhash-1.0.2.dist-info/top_level.txt
sqzhash-1.0.2.dist-info/RECORD
