Metadata-Version: 2.1
Name: sqzhash
Version: 1.0.2
Summary: SqzHash is a custom cryptographic hash algorithm implementation designed to compute hash values for strings and files.
Author: Squizoff
Requires-Python: >=3.6
License-File: LICENSE
